intel_npu_acceleration_library/__init__.py
intel_npu_acceleration_library/_version.py
intel_npu_acceleration_library/compiler.py
intel_npu_acceleration_library/device.py
intel_npu_acceleration_library/dtypes.py
intel_npu_acceleration_library/modelling.py
intel_npu_acceleration_library/optimizations.py
intel_npu_acceleration_library/quantization.py
intel_npu_acceleration_library/backend/__init__.py
intel_npu_acceleration_library/backend/base.py
intel_npu_acceleration_library/backend/bindings.py
intel_npu_acceleration_library/backend/compression.py
intel_npu_acceleration_library/backend/convolution.py
intel_npu_acceleration_library/backend/factory.py
intel_npu_acceleration_library/backend/linear.py
intel_npu_acceleration_library/backend/matmul.py
intel_npu_acceleration_library/backend/mlp.py
intel_npu_acceleration_library/backend/ops.py
intel_npu_acceleration_library/backend/qlinear.py
intel_npu_acceleration_library/backend/qmatmul.py
intel_npu_acceleration_library/backend/runtime.py
intel_npu_acceleration_library/backend/sdpa.py
intel_npu_acceleration_library/backend/tensor.py
intel_npu_acceleration_library/backend/utils.py
intel_npu_acceleration_library/external/openvino/__init__.py
intel_npu_acceleration_library/external/openvino/_pyopenvino.cp310-win_amd64.pyd
intel_npu_acceleration_library/external/openvino/_pyopenvino.cp311-win_amd64.pyd
intel_npu_acceleration_library/external/openvino/_pyopenvino.cp312-win_amd64.pyd
intel_npu_acceleration_library/external/openvino/_pyopenvino.cp38-win_amd64.pyd
intel_npu_acceleration_library/external/openvino/_pyopenvino.cp39-win_amd64.pyd
intel_npu_acceleration_library/external/openvino/utils.py
intel_npu_acceleration_library/external/openvino/_offline_transformations/__init__.py
intel_npu_acceleration_library/external/openvino/experimental/__init__.py
intel_npu_acceleration_library/external/openvino/frontend/__init__.py
intel_npu_acceleration_library/external/openvino/frontend/frontend.py
intel_npu_acceleration_library-1.4.0.dist-info/LICENSE
intel_npu_acceleration_library-1.4.0.dist-info/METADATA
intel_npu_acceleration_library-1.4.0.dist-info/WHEEL
intel_npu_acceleration_library-1.4.0.dist-info/top_level.txt
intel_npu_acceleration_library-1.4.0.dist-info/RECORD
