Metadata-Version: 2.1
Name: intel_npu_acceleration_library
Version: 1.4.0
Summary: Intel® NPU Acceleration Library
Home-page: https://github.com/intel/intel-npu-acceleration-library
Author: Alessandro Palla
Author-email: alessandro.palla@intel.com
License: Apache License 2.0
Keywords: intel-npu-acceleration-library,machine learning,llm,intel core ultra
Classifier: Development Status :: 4 - Beta
Classifier: Intended Audience :: Developers
Classifier: Intended Audience :: Education
Classifier: Intended Audience :: Science/Research
Classifier: License :: OSI Approved :: Apache Software License
Classifier: Topic :: Scientific/Engineering
Classifier: Topic :: Scientific/Engineering :: Mathematics
Classifier: Topic :: Scientific/Engineering :: Artificial Intelligence
Classifier: Topic :: Software Development
Classifier: Topic :: Software Development :: Libraries
Classifier: Topic :: Software Development :: Libraries :: Python Modules
Classifier: Programming Language :: C++
Classifier: Programming Language :: Python :: 3
Classifier: Programming Language :: Python :: 3 :: Only
Classifier: Programming Language :: Python :: 3.8
Classifier: Programming Language :: Python :: 3.9
Classifier: Programming Language :: Python :: 3.10
Classifier: Programming Language :: Python :: 3.11
Classifier: Programming Language :: Python :: 3.12
Requires-Python: >=3.8
License-File: LICENSE
Requires-Dist: numpy
Requires-Dist: torch
Requires-Dist: transformers>=4.43.0
Requires-Dist: neural-compressor
Provides-Extra: dev
Requires-Dist: pytest; extra == "dev"
Requires-Dist: pytest-xdist; extra == "dev"
Requires-Dist: pytest-cov; extra == "dev"
Requires-Dist: scikit-learn<=1.5.2; extra == "dev"
Requires-Dist: pre-commit; sys_platform == "darwin" and extra == "dev"
Requires-Dist: sphinx; extra == "dev"
Requires-Dist: breathe; extra == "dev"
Requires-Dist: sphinx-book-theme; extra == "dev"
Requires-Dist: myst-parser; extra == "dev"
Requires-Dist: ghp-import; extra == "dev"
Requires-Dist: pyroma; extra == "dev"
Requires-Dist: mypy; extra == "dev"
